MANIFEST.in
README.md
setup.py
text_rank/__init__.py
text_rank/demo.py
text_rank/graph.py
text_rank/keywords.py
text_rank/main.py
text_rank/summarize.py
text_rank/text_rank.py
text_rank/utils.py
text_rank.egg-info/PKG-INFO
text_rank.egg-info/SOURCES.txt
text_rank.egg-info/dependency_links.txt
text_rank.egg-info/entry_points.txt
text_rank.egg-info/requires.txt
text_rank.egg-info/top_level.txt
text_rank/data/automatic-summarization-sents.json
text_rank/data/automatic-summarization-tokens.json
text_rank/data/paper-example-keywords.json
text_rank/data/paper-example-summarize.json