Metadata-Version: 2.1
Name: text-rank
Version: 0.3.4
Summary: Text Rank
Home-page: https://github.com/blester125/text_rank
Author: blester125
Author-email: blester125@gmail.com
License: MIT
Download-URL: https://github.com/blester125/text_rank/archive/0.3.4.tar.gz
Keywords: NLP
Platform: UNKNOWN
Classifier: Topic :: Scientific/Engineering
Classifier: Programming Language :: Python :: 3 :: Only
Classifier: Intended Audience :: Science/Research
Classifier: Intended Audience :: Developers
Classifier: Natural Language :: English
Classifier: Environment :: Console
Classifier: Development Status :: 3 - Alpha
Classifier: License :: OSI Approved :: MIT License
Requires-Python: >=3.6
Provides-Extra: test
